setup.py
telegramlog/__init__.py
telegramlog/constants.py
telegramlog/setup.py
telegramlog.egg-info/PKG-INFO
telegramlog.egg-info/SOURCES.txt
telegramlog.egg-info/dependency_links.txt
telegramlog.egg-info/requires.txt
telegramlog.egg-info/top_level.txt
telegramlog/agent/__init__.py
telegramlog/agent/agent.py
telegramlog/agent/log.py
telegramlog/agent/utils.py
telegramlog/agent/backends/__init__.py
telegramlog/agent/backends/send_tele.py
telegramlog/api/__init__.py
telegramlog/api/client.py
telegramlog/api/log_handler.py